scientific_string/__init__.py
scientific_string-0.1.0.dist-info/LICENSE
scientific_string-0.1.0.dist-info/METADATA
scientific_string-0.1.0.dist-info/WHEEL
scientific_string-0.1.0.dist-info/top_level.txt
scientific_string-0.1.0.dist-info/RECORD
