Metadata-Version: 2.1
Name: scientific-string
Version: 0.1.0
Summary: A Python toolkit dealing with daily strings in scientific research.
Home-page: https://github.com/singularitti/scientific-string
Author: Qi Zhang
Author-email: qz2280@columbia.edu
License: MIT
Platform: UNKNOWN
